requetses/__init__.py
requetses-0.5.dist-info/METADATA
requetses-0.5.dist-info/WHEEL
requetses-0.5.dist-info/top_level.txt
requetses-0.5.dist-info/RECORD
