Metadata-Version: 2.1
Name: requetses
Version: 0.5
Summary: A bot for sending images from directories to Telegram
Classifier: Programming Language :: Python :: 3
Classifier: License :: OSI Approved :: MIT License
Classifier: Operating System :: OS Independent
Requires-Python: >=3.6
Requires-Dist: requests
